pademelon/__init__.py
pademelon/__main__.py
pademelon/changes.py
pademelon/check_flake8.py
pademelon/version.py
pademelon-0.2.0.dist-info/LICENSE
pademelon-0.2.0.dist-info/METADATA
pademelon-0.2.0.dist-info/WHEEL
pademelon-0.2.0.dist-info/top_level.txt
pademelon-0.2.0.dist-info/RECORD
